{"message_id":359,"from":{"id":6662926132,"is_bot":false,"first_name":"Emma","username":"emma_ri","language_code":"zh-hans"},"chat":{"id":6662926132,"first_name":"Emma","username":"emma_ri","type":"private"},"date":1721350748,"text":"/b","entities":[{"offset":0,"length":2,"type":"bot_command"}]},
{"message_id":361,"from":{"id":6662926132,"is_bot":false,"first_name":"Emma","username":"emma_ri","language_code":"zh-hans"},"chat":{"id":6662926132,"first_name":"Emma","username":"emma_ri","type":"private"},"date":1721350769,"text":"/c","entities":[{"offset":0,"length":2,"type":"bot_command"}]},
{"message_id":363,"from":{"id":6662926132,"is_bot":false,"first_name":"Emma","username":"emma_ri","language_code":"zh-hans"},"chat":{"id":6662926132,"first_name":"Emma","username":"emma_ri","type":"private"},"date":1721350781,"text":"/c","entities":[{"offset":0,"length":2,"type":"bot_command"}]},
{"message_id":365,"from":{"id":6662926132,"is_bot":false,"first_name":"Emma","username":"emma_ri","language_code":"zh-hans"},"chat":{"id":6662926132,"first_name":"Emma","username":"emma_ri","type":"private"},"date":1721350797,"text":"/q","entities":[{"offset":0,"length":2,"type":"bot_command"}]},
{"message_id":367,"from":{"id":6662926132,"is_bot":false,"first_name":"Emma","username":"emma_ri","language_code":"zh-hans"},"chat":{"id":6662926132,"first_name":"Emma","username":"emma_ri","type":"private"},"date":1721351003,"text":"/b","entities":[{"offset":0,"length":2,"type":"bot_command"}]},
{"message_id":369,"from":{"id":6662926132,"is_bot":false,"first_name":"Emma","username":"emma_ri","language_code":"zh-hans"},"chat":{"id":6662926132,"first_name":"Emma","username":"emma_ri","type":"private"},"date":1721351010,"text":"/c","entities":[{"offset":0,"length":2,"type":"bot_command"}]},
{"message_id":371,"from":{"id":6662926132,"is_bot":false,"first_name":"Emma","username":"emma_ri","language_code":"zh-hans"},"chat":{"id":6662926132,"first_name":"Emma","username":"emma_ri","type":"private"},"date":1721356375,"text":"/b","entities":[{"offset":0,"length":2,"type":"bot_command"}]},
